{
  "date": "2025-09-29",
  "generated_at": "2025-09-29T03:20:50.145243",
  "sources": {
    "medium_articles": [],
    "telegram_messages": [],
    "github_activities": [],
    "discord_messages": [],
    "forum_posts": [],
    "news_articles": [],
    "onchain_data": {},
    "documentation": []
  },
  "metadata": {
    "total_items": 0,
    "sources_processed": [],
    "resource_usage": {
      "peak_memory_gb": 0.0145416259765625,
      "memory_status": "OK",
      "disk_status": "OK",
      "processing_time": 0.002257823944091797
    }
  }
}